[{"title":"git命令备忘录","uid":"deb07f2084ce5c6636760b3189f1eaa0","slug":"git命令备忘录","date":"2022-03-05T03:08:36.000Z","updated":"2022-03-05T03:09:17.510Z","comments":true,"path":"api/articles/git命令备忘录.json","cover":null,"text":" git init 初始化版本库 git add 每次提交前都要添加 git commit -m “修改信息” git log 打印提交记录 git diff readme 查看版本区别 git reset 回到某个版本 git reset --hard 版本代号 git ref...","link":"","photos":[],"count_time":{"symbolsCount":"1k","symbolsTime":"1 mins."},"categories":[{"name":"知识点","slug":"知识点","count":2,"path":"api/categories/知识点.json"}],"tags":[{"name":"git","slug":"git","count":2,"path":"api/tags/git.json"},{"name":"备忘录","slug":"备忘录","count":1,"path":"api/tags/备忘录.json"}],"author":{"name":"LIYUNFU","slug":"blog-author","avatar":"https://gitee.com/LUNIONT/img-url/raw/master/202201011746808.jpg","link":"/","description":"一个正在重塑知识的切图仔 <br /> @ <b>公众号:伯nulee</b>","socials":{"github":"https://gitee.com/LUNIONT","twitter":"","stackoverflow":"","wechat":"","qq":"","weibo":"","zhihu":"","csdn":"","juejin":"https://juejin.cn/user/2277843824292183","customs":{}}},"feature":true},{"title":"ajax基本使用及跨域过程","uid":"6f0689131b9192e324f81c8459e5c263","slug":"ajax基本使用及跨域过程","date":"2022-03-05T03:06:30.000Z","updated":"2022-03-05T03:07:17.270Z","comments":true,"path":"api/articles/ajax基本使用及跨域过程.json","cover":null,"text":"ajax 是什么：ajax是Asynchronous JavaScript and XML（异步 JavaScript 和 XMl）的简写 异步：异步得像服务器发送请求，在等待响应的过程中，不会阻塞当前页面，浏览器可以做自己的事情。直到成功获取响应后，浏览器才开始处理响应数据 A...","link":"","photos":[],"count_time":{"symbolsCount":"2.7k","symbolsTime":"2 mins."},"categories":[{"name":"知识点","slug":"知识点","count":2,"path":"api/categories/知识点.json"}],"tags":[{"name":"ajax","slug":"ajax","count":1,"path":"api/tags/ajax.json"},{"name":"跨域","slug":"跨域","count":1,"path":"api/tags/跨域.json"}],"author":{"name":"LIYUNFU","slug":"blog-author","avatar":"https://gitee.com/LUNIONT/img-url/raw/master/202201011746808.jpg","link":"/","description":"一个正在重塑知识的切图仔 <br /> @ <b>公众号:伯nulee</b>","socials":{"github":"https://gitee.com/LUNIONT","twitter":"","stackoverflow":"","wechat":"","qq":"","weibo":"","zhihu":"","csdn":"","juejin":"https://juejin.cn/user/2277843824292183","customs":{}}},"feature":true},{"title":"远程服务器安装Docker并配置数据库","uid":"c123efc46127ac74fdea33d3d47fa7a0","slug":"远程服务器安装Docker并配置数据库","date":"2022-03-05T03:02:36.000Z","updated":"2022-03-05T03:03:21.177Z","comments":true,"path":"api/articles/远程服务器安装Docker并配置数据库.json","cover":null,"text":"Docker命令安装docker-desktop点击前往官网下载，一直下一步安装即可 如果出现错误，说明wsl内核未更新到wsl2，点击下载安装之后重启docker-desktop即可 查看已安装docker版本docker --version 安装docker-compose ...","link":"","photos":[],"count_time":{"symbolsCount":"2.6k","symbolsTime":"2 mins."},"categories":[{"name":"实战","slug":"实战","count":5,"path":"api/categories/实战.json"}],"tags":[{"name":"数据库","slug":"数据库","count":2,"path":"api/tags/数据库.json"},{"name":"Docker","slug":"Docker","count":1,"path":"api/tags/Docker.json"}],"author":{"name":"LIYUNFU","slug":"blog-author","avatar":"https://gitee.com/LUNIONT/img-url/raw/master/202201011746808.jpg","link":"/","description":"一个正在重塑知识的切图仔 <br /> @ <b>公众号:伯nulee</b>","socials":{"github":"https://gitee.com/LUNIONT","twitter":"","stackoverflow":"","wechat":"","qq":"","weibo":"","zhihu":"","csdn":"","juejin":"https://juejin.cn/user/2277843824292183","customs":{}}},"feature":true}]